whoi_directory_tree/directory_tree.py
whoi_directory_tree-0.0.2.dist-info/LICENSE
whoi_directory_tree-0.0.2.dist-info/METADATA
whoi_directory_tree-0.0.2.dist-info/WHEEL
whoi_directory_tree-0.0.2.dist-info/top_level.txt
whoi_directory_tree-0.0.2.dist-info/RECORD
