Metadata-Version: 2.1
Name: whoi-directory-tree
Version: 0.0.2
Summary: whoi_directory_tree
Home-page: https://git.whoi.edu/acomms/whoi_directory_tree/
Author: WHOI Acomms Group
Classifier: License :: OSI Approved :: GNU General Public License v3 (GPLv3)
License-File: LICENSE
